kevin_dl/__init__.py
kevin_dl/deploy/__init__.py
kevin_dl/deploy/build_onnx_from_ckpt.py
kevin_dl/deploy/convert_torch_to_caffe.py
kevin_dl/deploy/convert_torch_to_onnx.py
kevin_dl/deploy/fix_onnx_initializers.py
kevin_dl/deploy/run_onnx_model.py
kevin_dl/deploy/utils/__init__.py
kevin_dl/deploy/utils/model_wrapper_for_dict_in_out.py
kevin_dl/models/__init__.py
kevin_dl/models/api/__init__.py
kevin_dl/models/api/run_kevin_sdk_face_detect.py
kevin_dl/models/api/run_model.py
kevin_dl/models/api/utils/__init__.py
kevin_dl/models/api/utils/fix_image_channel_order.py
kevin_dl/models/api/utils/import_function_from_file.py
kevin_dl/models/api/utils/parse_model_name.py
kevin_dl/models/api/utils/parse_postprocess.py
kevin_dl/models/api/utils/parse_preprocess.py
kevin_dl/models/api/utils/variable.py
kevin_dl/tools/__init__.py
kevin_dl/tools/variable.py
kevin_dl/tools/ckpts_management/__init__.py
kevin_dl/tools/ckpts_management/ckpt_manager.py
kevin_dl/tools/ckpts_management/find_trials.py
kevin_dl/tools/face/__init__.py
kevin_dl/tools/face/alignment/__init__.py
kevin_dl/tools/face/alignment/by_bbox/__init__.py
kevin_dl/tools/face/alignment/by_bbox/affine_trans.py
kevin_dl/tools/face/alignment/by_landmarks/__init__.py
kevin_dl/tools/face/alignment/by_landmarks/affine_trans.py
kevin_dl/tools/face/alignment/by_landmarks/prn_method.py
kevin_dl/tools/face/alignment/utils/__init__.py
kevin_dl/tools/face/alignment/utils/warp_affine_and_crop_by_point_pairs.py
kevin_dl/tools/face/detect/__init__.py
kevin_dl/tools/face/detect/mtcnn_detector.py
kevin_dl/tools/face/detect/sfd_detector.py
kevin_dl/tools/face/pipeline/__init__.py
kevin_dl/tools/face/pipeline/generate_face_dataset_from_image_dataset.py
kevin_dl/tools/face/utils/__init__.py
kevin_dl/tools/face/utils/cal_2d_affine_trans_matrix.py
kevin_dl/tools/face/utils/gaussian_filter_1d.py
kevin_dl/tools/face/utils/parse_landmarks.py
kevin_dl/tools/face/utils/perform_2d_affine_trans.py
kevin_dl/tools/face/utils/plot_bbox_and_landmarks.py
kevin_dl-0.1.1.dist-info/LICENSE.txt
kevin_dl-0.1.1.dist-info/METADATA
kevin_dl-0.1.1.dist-info/WHEEL
kevin_dl-0.1.1.dist-info/top_level.txt
kevin_dl-0.1.1.dist-info/RECORD
