Metadata-Version: 2.1
Name: kevin-dl
Version: 0.1.1
Summary: 深度学习相关工具与框架
Home-page: https://github.com/cantbeblank96/kevin_dl_release
Author: kevin hsu
Author-email: xukaiming1996@163.com
License: MIT
Keywords: mathematics,pytorch,numpy,machine-learning,algorithm
Classifier: License :: OSI Approved :: MIT License
Classifier: Programming Language :: Python
Classifier: Programming Language :: Python :: 3
Requires-Python: >=3.6
License-File: LICENSE.txt
Requires-Dist: torch >=1.2.0
Requires-Dist: numpy >=1.19.0
Requires-Dist: kevin-toolbox >=1.4.5
Provides-Extra: plot
Requires-Dist: matplotlib >=3.0 ; extra == 'plot'
Provides-Extra: test
Requires-Dist: pytest >=6.2.5 ; extra == 'test'
Requires-Dist: line-profiler >=3.5 ; extra == 'test'
